lando_core/README.md
lando_core/__init__.py
lando_core/main.py
lando_core/requirements.txt
lando_core/chat/__init__.py
lando_core/chat/chatGPT.py
lando_core/util/__init__.py
lando_core/util/cache.py
lando_core/util/cos.py
lando_core/util/email.py
lando_core/util/tts.py
lando_core-0.0.2.dist-info/LICENSE
lando_core-0.0.2.dist-info/METADATA
lando_core-0.0.2.dist-info/WHEEL
lando_core-0.0.2.dist-info/top_level.txt
lando_core-0.0.2.dist-info/RECORD
